tfkan/__init__.py
tfkan/layers/__init__.py
tfkan/layers/base.py
tfkan/layers/convolution.py
tfkan/layers/dense.py
tfkan/ops/__init__.py
tfkan/ops/grid.py
tfkan/ops/spline.py
tfkan-0.1.1.data/data/requirements.txt
tfkan-0.1.1.dist-info/LICENSE
tfkan-0.1.1.dist-info/METADATA
tfkan-0.1.1.dist-info/WHEEL
tfkan-0.1.1.dist-info/top_level.txt
tfkan-0.1.1.dist-info/RECORD
