Metadata-Version: 2.1
Name: tfkan
Version: 0.1.1
Summary: A Tensorflow implementation of KANs
Author: Xavier Camel
Classifier: Programming Language :: Python :: 3
Classifier: License :: OSI Approved :: MIT License
Classifier: Operating System :: OS Independent
Requires-Python: >=3.7
License-File: LICENSE
Requires-Dist: tensorflow <=2.15.1,>=2.10.0
Requires-Dist: keras <=2.15.1
